{"appId":"altair","appShortcutName":"altair","appDisplayName":"altair","authorId":"1","releaseTagName":"ahqstore","downloadUrls":{"0":{"installerType":"LinuxAppImage","asset":"url","url":"https://github.com/altair-graphql/altair/releases/download/v8.2.5/altair_8.2.5_x86_64_linux.AppImage"}},"install":{"win32":null,"winarm":null,"linux":{"assetId":0},"linuxArm64":null,"linuxArm7":null,"android":null},"displayImages":[1],"description":"The best graphQL client you will ever need","repo":{"author":"AppImage","repo":"appimage.github.io"},"version":"9ce9d1865cbaaac0cbbe7c281e03b665c938729376d8e12fd237565ef2bbe971","site":null,"source":"appimages","license_or_tos":"MIT","resources":null,"verified":false}