{"appId":"avogadro","appShortcutName":"avogadro","appDisplayName":"avogadro","authorId":"1","releaseTagName":"ahqstore","downloadUrls":{"0":{"installerType":"LinuxAppImage","asset":"url","url":"https://github.com/OpenChemistry/avogadrolibs/releases/download/1.100.0/Avogadro2-x86_64.AppImage"}},"install":{"win32":null,"winarm":null,"linux":{"assetId":0},"linuxArm64":null,"linuxArm7":null,"android":null},"displayImages":[1],"description":"Advanced molecular editor","repo":{"author":"AppImage","repo":"appimage.github.io"},"version":"ffc59eed81f1d0d41015da911563557fb610cfbfc5ac77a7ced91d8c098d2a5e","site":null,"source":"appimages","license_or_tos":"","resources":null,"verified":false}