{"appId":"bottlenose","appShortcutName":"bottlenose","appDisplayName":"bottlenose","authorId":"1","releaseTagName":"ahqstore","downloadUrls":{},"install":{"win32":null,"winarm":null,"linux":null,"linuxArm64":null,"linuxArm7":null,"android":null},"displayImages":[1],"description":"Bottlenose is a front-end for video game emulators, use it to install and auto-update texture packs!","repo":{"author":"AppImage","repo":"appimage.github.io"},"version":"bfbadd47dc9de8a2a89857da941d865cb69aa3c9d4dcd9824590fef7bd57c18d","site":null,"source":"appimages","license_or_tos":"MIT","resources":null,"verified":false}