{"appId":"FF-Password-Exporter","appShortcutName":"FF-Password-Exporter","appDisplayName":"FF-Password-Exporter","authorId":"1","releaseTagName":"ahqstore","downloadUrls":{"0":{"installerType":"LinuxAppImage","asset":"url","url":"https://github.com/kspearrin/ff-password-exporter/releases/download/v1.2.0/FF-Password-Exporter-1.2.0-x86_64.AppImage"}},"install":{"win32":null,"winarm":null,"linux":{"assetId":0},"linuxArm64":null,"linuxArm7":null,"android":null},"displayImages":[1],"description":"Easily export your saved passwords from Firefox.","repo":{"author":"AppImage","repo":"appimage.github.io"},"version":"3d9bf7c84b0c3d7c7431f66a894247f1763de54bddd47b47a14cd45a7ef16083","site":null,"source":"appimages","license_or_tos":"GPL-3.0","resources":null,"verified":false}