{"appId":"Joy2DroidX","appShortcutName":"Joy2DroidX","appDisplayName":"Joy2DroidX","authorId":"1","releaseTagName":"ahqstore","downloadUrls":{"0":{"installerType":"LinuxAppImage","asset":"url","url":"https://github.com/OzymandiasTheGreat/Joy2DroidX-server/releases/download/v0.1.0/Joy2DroidX-server-0.1.0-x86_64.AppImage"}},"install":{"win32":null,"winarm":null,"linux":{"assetId":0},"linuxArm64":null,"linuxArm7":null,"android":null},"displayImages":[],"description":"Virtual gamepad server","repo":{"author":"AppImage","repo":"appimage.github.io"},"version":"41526347e829bb13c01625f8eb7d26283eca49c8ef952c32628743a9dd6deec4","site":null,"source":"appimages","license_or_tos":"GPL-3.0","resources":null,"verified":false}