{"appId":"LibreOfficePreRelease","appShortcutName":"LibreOfficePreRelease","appDisplayName":"LibreOfficePreRelease","authorId":"1","releaseTagName":"ahqstore","downloadUrls":{"0":{"installerType":"LinuxAppImage","asset":"url","url":"https://libreoffice.soluzioniopen.com/pre-releases/standard/LibreOffice-6.0.0.3.standard.help-x86_64.AppImage"}},"install":{"win32":null,"winarm":null,"linux":{"assetId":0},"linuxArm64":null,"linuxArm7":null,"android":null},"displayImages":[1],"description":"The office productivity suite compatible to the open and standardized ODF document format. Supported by The Document Foundation.","repo":{"author":"AppImage","repo":"appimage.github.io"},"version":"b6c4b0190aebd4f7509d2bfed09b53862d25c340ac22b83c6fe41e343d1b739d","site":null,"source":"appimages","license_or_tos":"","resources":null,"verified":false}