{"appId":"MMapper","appShortcutName":"MMapper","appDisplayName":"MMapper","authorId":"1","releaseTagName":"ahqstore","downloadUrls":{"0":{"installerType":"LinuxAppImage","asset":"url","url":"https://github.com/MUME/MMapper/releases/download/v25.06.0/MMapper-25.06.0-x86_64.AppImage"}},"install":{"win32":null,"winarm":null,"linux":{"assetId":0},"linuxArm64":null,"linuxArm7":null,"android":null},"displayImages":[],"description":"MUME Mapper","repo":{"author":"AppImage","repo":"appimage.github.io"},"version":"1332c8b818e22263b67080d6696d38bdbcc69239ae35a008f0bf385a0fe7b642","site":null,"source":"appimages","license_or_tos":"GPL-2.0+","resources":null,"verified":false}