{"appId":"MyPaint","appShortcutName":"MyPaint","appDisplayName":"MyPaint","authorId":"1","releaseTagName":"ahqstore","downloadUrls":{},"install":{"win32":null,"winarm":null,"linux":null,"linuxArm64":null,"linuxArm7":null,"android":null},"displayImages":[1],"description":"Painting program for digital artists","repo":{"author":"AppImage","repo":"appimage.github.io"},"version":"110b710283d1df17d9bf99e89edcb2f02bfa3b0fa95581ea27c1f3bf425c7391","site":null,"source":"appimages","license_or_tos":"GPL-2.0","resources":null,"verified":false}