{"appId":"qtchan.md","appShortcutName":"qtchan.md","appDisplayName":"qtchan.md","authorId":"6adfb183a4a2c94a2f92dab5ade762a47889a5a1","releaseTagName":"ahqstore","downloadUrls":{"0":{"installerType":"LinuxAppImage","asset":"<-- NO NEED -->","url":"https://github.com/AppImage/appimage.github.io/releases/download/ahqstore/<-- NO NEED -->"}},"install":{"win32":null,"winarm":null,"linux":{"assetId":0},"linuxArm64":null,"linuxArm7":null,"android":null},"displayImages":[1],"description":"4chan browser in qt5","repo":{"author":"AppImage","repo":"appimage.github.io"},"version":"e5d9b28b583fc8958f306f4b965cc65ef7b754a2473b973548c461b49bb1706d","site":null,"source":"appimages","license_or_tos":"","resources":null,"verified":false}