{"appId":"retail.md","appShortcutName":"retail.md","appDisplayName":"retail.md","authorId":"6adfb183a4a2c94a2f92dab5ade762a47889a5a1","releaseTagName":"ahqstore","downloadUrls":{"0":{"installerType":"LinuxAppImage","asset":"<-- NO NEED -->","url":"https://github.com/AppImage/appimage.github.io/releases/download/ahqstore/<-- NO NEED -->"}},"install":{"win32":null,"winarm":null,"linux":{"assetId":0},"linuxArm64":null,"linuxArm7":null,"android":null},"displayImages":[1],"description":"Retail Desktop App by Evoluzin","repo":{"author":"AppImage","repo":"appimage.github.io"},"version":"eb52f04ce3ee0b833e1cf579d89e8565b9b4c5ddc80d4916c5da17adbc7f84c1","site":null,"source":"appimages","license_or_tos":"","resources":null,"verified":false}