{"appId":"Rubber_Band_Audio.md","appShortcutName":"Rubber_Band_Audio.md","appDisplayName":"Rubber_Band_Audio.md","authorId":"6adfb183a4a2c94a2f92dab5ade762a47889a5a1","releaseTagName":"ahqstore","downloadUrls":{"0":{"installerType":"LinuxAppImage","asset":"<-- NO NEED -->","url":"https://github.com/AppImage/appimage.github.io/releases/download/ahqstore/<-- NO NEED -->"}},"install":{"win32":null,"winarm":null,"linux":{"assetId":0},"linuxArm64":null,"linuxArm7":null,"android":null},"displayImages":[1],"description":"","repo":{"author":"AppImage","repo":"appimage.github.io"},"version":"fe40def33d5e57dd99c92cf1770a88588a03f3f6a98996b17e261715577b030c","site":null,"source":"appimages","license_or_tos":"","resources":null,"verified":false}