{"appId":"sunshine","appShortcutName":"sunshine","appDisplayName":"sunshine","authorId":"1","releaseTagName":"ahqstore","downloadUrls":{},"install":{"win32":null,"winarm":null,"linux":null,"linuxArm64":null,"linuxArm7":null,"android":null},"displayImages":[],"description":"Sunshine is a self-hosted game stream host for Moonlight.","repo":{"author":"AppImage","repo":"appimage.github.io"},"version":"cb6378a5e1968f226b567eb6e088f9a058fb3a7112c679ec72b8291e0845bbcb","site":null,"source":"appimages","license_or_tos":"GPL-3.0","resources":null,"verified":false}