{"appId":"SyncMyL2P","appShortcutName":"SyncMyL2P","appDisplayName":"SyncMyL2P","authorId":"1","releaseTagName":"ahqstore","downloadUrls":{},"install":{"win32":null,"winarm":null,"linux":null,"linuxArm64":null,"linuxArm7":null,"android":null},"displayImages":[1],"description":"Sync-my-L2P — L2P synchronisation tool","repo":{"author":"AppImage","repo":"appimage.github.io"},"version":"307c5d65b912a3fd387646a34cf8b9a31f51fd5bf4b662596a04dd9947e9e7f2","site":null,"source":"appimages","license_or_tos":"","resources":null,"verified":false}