{"appId":"tagspaces","appShortcutName":"tagspaces","appDisplayName":"tagspaces","authorId":"1","releaseTagName":"ahqstore","downloadUrls":{"0":{"installerType":"LinuxAppImage","asset":"url","url":"https://github.com/tagspaces/tagspaces/releases/download/v6.4.4/tagspaces-linux-x86_64-6.4.4.AppImage"}},"install":{"win32":null,"winarm":null,"linux":{"assetId":0},"linuxArm64":null,"linuxArm7":null,"android":null},"displayImages":[1],"description":"Offline file organizer and browser with tagging support.","repo":{"author":"AppImage","repo":"appimage.github.io"},"version":"32646fccf1977ffdf3c31ec9d7b4cc48766337f44091951b9da9b600bb32183a","site":null,"source":"appimages","license_or_tos":"","resources":null,"verified":false}