{"appId":"Tagstoo","appShortcutName":"Tagstoo","appDisplayName":"Tagstoo","authorId":"1","releaseTagName":"ahqstore","downloadUrls":{"0":{"installerType":"LinuxAppImage","asset":"url","url":"https://www.appimagehub.com/p/1192626/startdownload?file_id=1537111294&file_name=Tagstoo_linux64.AppImage&file_type=application/x-executable&file_size=54142374&url=https%3A%2F%2Fdl.opendesktop.org%2Fapi%2Ffiles%2Fdownload%2Fid%2F1537111294%2Fs%2F730633380a2295608baf2ac7e047263a%2Ft%2F1537478597%2Fu%2F%2FTagstoo_linux64.AppImage"}},"install":{"win32":null,"winarm":null,"linux":{"assetId":0},"linuxArm64":null,"linuxArm7":null,"android":null},"displayImages":[1],"description":"Tagstoo tagging application","repo":{"author":"AppImage","repo":"appimage.github.io"},"version":"fa63de2d240453dca03092d789938ecca75583f21da527f745d30b2fcfb2a6a5","site":null,"source":"appimages","license_or_tos":"","resources":null,"verified":false}