{"appId":"TeleDrive","appShortcutName":"TeleDrive","appDisplayName":"TeleDrive","authorId":"1","releaseTagName":"ahqstore","downloadUrls":{"0":{"installerType":"LinuxAppImage","asset":"url","url":"https://github.com/khrj/teledrive/releases/download/v1.2.0/TeleDrive-1.2.0-x86_64.AppImage"}},"install":{"win32":null,"winarm":null,"linux":{"assetId":0},"linuxArm64":null,"linuxArm7":null,"android":null},"displayImages":[1],"description":"An app that lets you automatically backup to Telegram Saved Messages","repo":{"author":"AppImage","repo":"appimage.github.io"},"version":"4b5a83741a7dc75effbadb57d278404087e7afb552e7c2ac638dd07ceb525ea0","site":null,"source":"appimages","license_or_tos":"","resources":null,"verified":false}