{"appId":"Thunderbird_Nightly","appShortcutName":"Thunderbird_Nightly","appDisplayName":"Thunderbird_Nightly","authorId":"1","releaseTagName":"ahqstore","downloadUrls":{},"install":{"win32":null,"winarm":null,"linux":null,"linuxArm64":null,"linuxArm7":null,"android":null},"displayImages":[1],"description":"Send and receive mail with Thunderbird","repo":{"author":"AppImage","repo":"appimage.github.io"},"version":"eec37b77c10f4713fda9a657ca2b03e6cd66fe5509c4450925e721b129f3b22f","site":null,"source":"appimages","license_or_tos":"","resources":null,"verified":false}