{"appId":"WebDesktop","appShortcutName":"WebDesktop","appDisplayName":"WebDesktop","authorId":"1","releaseTagName":"ahqstore","downloadUrls":{},"install":{"win32":null,"winarm":null,"linux":null,"linuxArm64":null,"linuxArm7":null,"android":null},"displayImages":[1],"description":"WebDesktop make apps with just a text editor and nodejs.","repo":{"author":"AppImage","repo":"appimage.github.io"},"version":"38c9df00f4a1fd10c41815e4ba34346475a9ecb0e1d56fe5dfeeddd818941a2b","site":null,"source":"appimages","license_or_tos":"","resources":null,"verified":false}