{"appId":"wxMaxima","appShortcutName":"wxMaxima","appDisplayName":"wxMaxima","authorId":"1","releaseTagName":"ahqstore","downloadUrls":{},"install":{"win32":null,"winarm":null,"linux":null,"linuxArm64":null,"linuxArm7":null,"android":null},"displayImages":[],"description":"wxmaxima","repo":{"author":"AppImage","repo":"appimage.github.io"},"version":"de04717a3f5f480acc389137301b1e18a819f9877d61ab735bf8ef1f3c215ec6","site":null,"source":"appimages","license_or_tos":"MIT","resources":null,"verified":false}