{"appId":"XMedCon","appShortcutName":"XMedCon","appDisplayName":"XMedCon","authorId":"1","releaseTagName":"ahqstore","downloadUrls":{"0":{"installerType":"LinuxAppImage","asset":"url","url":"https://pilotfiber.dl.sourceforge.net/project/xmedcon/XMedCon-AppImage/0.21.2/XMedCon-x86_64.AppImage"}},"install":{"win32":null,"winarm":null,"linux":{"assetId":0},"linuxArm64":null,"linuxArm7":null,"android":null},"displayImages":[1],"description":"An open-source toolkit for medical image conversion","repo":{"author":"AppImage","repo":"appimage.github.io"},"version":"490bdd7b81c796c941129b758bf5bf00fb189b25af4ce1ac3ba193987d9f517c","site":null,"source":"appimages","license_or_tos":"","resources":null,"verified":false}